MANIFEST.in
README.rst
setup.cfg
setup.py
versioneer.py
daskathon/__init__.py
daskathon/_version.py
daskathon/cli.py
daskathon/core.py
daskathon.egg-info/PKG-INFO
daskathon.egg-info/SOURCES.txt
daskathon.egg-info/dependency_links.txt
daskathon.egg-info/entry_points.txt
daskathon.egg-info/not-zip-safe
daskathon.egg-info/requires.txt
daskathon.egg-info/top_level.txt