Metadata-Version: 1.0
Name: daskathon
Version: 1.3.1
Summary: Deploy Dask on Marathon
Home-page: http://github.com/daskos/daskathon/
Author: Krisztian Szucs
Author-email: szucs.krisztian@gmail.com
License: BSD
Platform: UNKNOWN
